asagg_lib/__init__.py
asagg_lib/asagg.py
asagg_lib/exceptions/__init__.py
asagg_lib/exceptions/parameters.py
asagg_lib/templates/class_template_file.pyi
asagg_lib/typing/__init__.py
asagg_lib/typing/generics.py
asagg_lib/utils/__init__.py
asagg_lib/utils/extractor.py
asagg_lib/utils/formatter.py
asagg_lib/utils/list_operations.py
asagg_lib/utils/validators.py
asagg_lib-0.1.1.dist-info/LICENSE.txt
asagg_lib-0.1.1.dist-info/METADATA
asagg_lib-0.1.1.dist-info/WHEEL
asagg_lib-0.1.1.dist-info/RECORD
