Metadata-Version: 2.1
Name: asagg-lib
Version: 0.1.1
Summary: The Asagg library (Auto Setter And Getter Generator) is a library inspired by another library that is in the Java environment, which is the Lombock library
License: GPL-3.0
Author: Pedro Augusto Barbosa Aparecido
Author-email: pedr.augustobarbosa.aparecido@gmail.com
Requires-Python: >=3.11,<4.0
Classifier: Development Status :: 5 - Production/Stable
Classifier: License :: OSI Approved :: GNU General Public License v3 (GPLv3)
Classifier: Natural Language :: English
Classifier: Natural Language :: Portuguese (Brazilian)
Classifier: Programming Language :: Python :: 3
Classifier: Programming Language :: Python :: 3.11
Classifier: Topic :: Software Development :: Libraries
Classifier: Topic :: Utilities
Project-URL: Bug Tracker, https://github.com/pedroaba/Asagg/issues
Project-URL: Code, https://github.com/pedroaba/Asagg
Project-URL: Documentation, https://asagg.readthedocs.io
